nlpfreq/__init__.py
nlpfreq/main.py
nlpfreq/core/__init__.py
nlpfreq/core/input_handler.py
nlpfreq/core/text_processor.py
nlpfreq-1.0.dist-info/LICENSE
nlpfreq-1.0.dist-info/METADATA
nlpfreq-1.0.dist-info/WHEEL
nlpfreq-1.0.dist-info/entry_points.txt
nlpfreq-1.0.dist-info/top_level.txt
nlpfreq-1.0.dist-info/RECORD
