Metadata-Version: 2.1
Name: nlpfreq
Version: 1.0
Summary: Advanced Feature-Rich CLI-based Word Frequency Analysis Tool
Home-page: https://github.com/vivekkdagar/NLPFreq
Author: Vivek Dagar
Author-email: vivekdagar2017@gmail.com
License: GNU General Public License v3.0
License-File: LICENSE
Requires-Dist: click
Requires-Dist: nltk
Requires-Dist: tabulate
Requires-Dist: wordcloud
Requires-Dist: matplotlib
Requires-Dist: seaborn
Requires-Dist: requests
Requires-Dist: beautifulsoup4
